{
  "image_path": "/Users/rlatldn20001114/on-device-image-privacy-detector/data/test_images/sample1.png",
  "overall_risk_level": "critical",
  "processing_time_ms": 29182.28578567505,
  "total_assessments": 15,
  "confirmed_risks": 5,
  "faces_pending_identity": 0,
  "detection_summary": {
    "faces": 1,
    "text_regions": 7,
    "objects": 5,
    "total": 13
  },
  "assessments": [
    {
      "detection_id": "91202fab-bf70-4daf-8eb9-e8ed6ce62719",
      "element_type": "face",
      "element_description": "Face (medium, high clarity)",
      "risk_type": "identity_exposure",
      "severity": "critical",
      "color_code": "#FF0000",
      "reasoning": "Tool-based assessment",
      "bbox": [
        410,
        172,
        242,
        305
      ],
      "requires_protection": true,
      "consent_status": "none",
      "consent_confidence": 0.0,
      "user_sensitivity_applied": "bystander_faces"
    },
    {
      "detection_id": "8c0c069c-cba7-46c8-aa10-2f67d23cca92",
      "element_type": "text",
      "element_description": "Text: Social Security",
      "risk_type": "information_disclosure",
      "severity": "low",
      "color_code": "#90EE90",
      "reasoning": "Tool-based assessment",
      "bbox": [
        222,
        1166,
        257,
        45
      ],
      "requires_protection": false,
      "consent_status": null,
      "consent_confidence": 0.0,
      "user_sensitivity_applied": "high"
    },
    {
      "detection_id": "9255fc25-e76b-4dac-a8f0-9641c0e8f969",
      "element_type": "text",
      "element_description": "Text: #:",
      "risk_type": "information_disclosure",
      "severity": "low",
      "color_code": "#90EE90",
      "reasoning": "Tool-based assessment -> VLM: Label-only text '#:' with no actual data after colon",
      "bbox": [
        486,
        1176,
        44,
        26
      ],
      "requires_protection": false,
      "consent_status": null,
      "consent_confidence": 0.0,
      "user_sensitivity_applied": "critical"
    },
    {
      "detection_id": "caf85437-870c-4c21-869b-fd6cdfc7e934",
      "element_type": "text",
      "element_description": "Text: 238-49-6521",
      "risk_type": "information_disclosure",
      "severity": "critical",
      "color_code": "#FF0000",
      "reasoning": "Tool-based assessment",
      "bbox": [
        211,
        1210,
        283,
        44
      ],
      "requires_protection": true,
      "consent_status": null,
      "consent_confidence": 0.0,
      "user_sensitivity_applied": "critical"
    },
    {
      "detection_id": "e693b60b-1072-46b1-890f-bffd91bebe0a_split_0",
      "element_type": "text",
      "element_description": "Text label: Bank Account",
      "risk_type": "information_disclosure",
      "severity": "low",
      "color_code": "#90EE90",
      "reasoning": "VLM review: Label text only, no actual data",
      "bbox": [
        226,
        1310,
        86,
        38
      ],
      "requires_protection": false,
      "consent_status": null,
      "consent_confidence": 0.0,
      "user_sensitivity_applied": "critical"
    },
    {
      "detection_id": "e693b60b-1072-46b1-890f-bffd91bebe0a_split_1",
      "element_type": "text",
      "element_description": "Text value: 8765 4321 0987",
      "risk_type": "information_disclosure",
      "severity": "critical",
      "color_code": "#FF0000",
      "reasoning": "VLM review: Contains actual bank account number",
      "bbox": [
        456,
        1300,
        94,
        42
      ],
      "requires_protection": true,
      "consent_status": null,
      "consent_confidence": 0.0,
      "user_sensitivity_applied": "critical"
    },
    {
      "detection_id": "eebecf76-d4c5-46e4-8f89-cddc3d158622_split_0",
      "element_type": "text",
      "element_description": "Text label: PIN",
      "risk_type": "information_disclosure",
      "severity": "low",
      "color_code": "#90EE90",
      "reasoning": "VLM review: Label text only, no actual data",
      "bbox": [
        229,
        1356,
        216,
        60
      ],
      "requires_protection": false,
      "consent_status": null,
      "consent_confidence": 0.0,
      "user_sensitivity_applied": "critical"
    },
    {
      "detection_id": "eebecf76-d4c5-46e4-8f89-cddc3d158622_split_1",
      "element_type": "text",
      "element_description": "Text value: 4821",
      "risk_type": "information_disclosure",
      "severity": "critical",
      "color_code": "#FF0000",
      "reasoning": "VLM review: Contains actual PIN",
      "bbox": [
        324,
        1358,
        119,
        55
      ],
      "requires_protection": true,
      "consent_status": null,
      "consent_confidence": 0.0,
      "user_sensitivity_applied": "critical"
    },
    {
      "detection_id": "d6287313-10c9-423c-aa78-56a0fee7ce1b",
      "element_type": "text",
      "element_description": "Text: Password:",
      "risk_type": "information_disclosure",
      "severity": "low",
      "color_code": "#90EE90",
      "reasoning": "Tool-based assessment",
      "bbox": [
        759,
        1143,
        168,
        55
      ],
      "requires_protection": false,
      "consent_status": null,
      "consent_confidence": 0.0,
      "user_sensitivity_applied": "high"
    },
    {
      "detection_id": "17ccd37c-3b1e-455c-9175-83e17eb39d8e",
      "element_type": "text",
      "element_description": "Text: Magicl231",
      "risk_type": "information_disclosure",
      "severity": "critical",
      "color_code": "#FF0000",
      "reasoning": "Tool-based assessment",
      "bbox": [
        747,
        1177,
        191,
        71
      ],
      "requires_protection": true,
      "consent_status": null,
      "consent_confidence": 0.0,
      "user_sensitivity_applied": "critical"
    },
    {
      "detection_id": "e75bda51-9441-4776-9fab-5117e8ba34d3",
      "element_type": "object",
      "element_description": "Object: laptop",
      "risk_type": "information_disclosure",
      "severity": "low",
      "color_code": "#90EE90",
      "reasoning": "Tool-based assessment",
      "bbox": [
        0,
        727,
        630,
        409
      ],
      "requires_protection": false,
      "consent_status": null,
      "consent_confidence": 0.0,
      "user_sensitivity_applied": "high"
    },
    {
      "detection_id": "101d70fe-4c6d-4c2e-a627-2a31d1cdf5bf",
      "element_type": "object",
      "element_description": "Object: cell phone",
      "risk_type": "information_disclosure",
      "severity": "low",
      "color_code": "#90EE90",
      "reasoning": "Tool-based assessment",
      "bbox": [
        0,
        1100,
        143,
        108
      ],
      "requires_protection": false,
      "consent_status": null,
      "consent_confidence": 0.0,
      "user_sensitivity_applied": "high"
    },
    {
      "detection_id": "8bb6886e-2649-40d5-b0c3-951eb78ff1e3",
      "element_type": "object",
      "element_description": "Object: book",
      "risk_type": "context_exposure",
      "severity": "low",
      "color_code": "#90EE90",
      "reasoning": "Tool-based assessment",
      "bbox": [
        75,
        1126,
        807,
        359
      ],
      "requires_protection": false,
      "consent_status": null,
      "consent_confidence": 0.0,
      "user_sensitivity_applied": "medium"
    },
    {
      "detection_id": "a69da92d-51a8-4905-820a-0e23f977c3b4",
      "element_type": "object",
      "element_description": "Object: book",
      "risk_type": "context_exposure",
      "severity": "low",
      "color_code": "#90EE90",
      "reasoning": "Tool-based assessment",
      "bbox": [
        110,
        1248,
        765,
        236
      ],
      "requires_protection": false,
      "consent_status": null,
      "consent_confidence": 0.0,
      "user_sensitivity_applied": "medium"
    },
    {
      "detection_id": "07893c9a-eabf-44e7-9d29-10dd80c2ae1a",
      "element_type": "object",
      "element_description": "Object: book",
      "risk_type": "context_exposure",
      "severity": "low",
      "color_code": "#90EE90",
      "reasoning": "Tool-based assessment",
      "bbox": [
        839,
        24,
        46,
        138
      ],
      "requires_protection": false,
      "consent_status": null,
      "consent_confidence": 0.0,
      "user_sensitivity_applied": "medium"
    }
  ]
}